env2installer/LICENSE
env2installer/README.MD
env2installer/__init__.py
env2installer/requirements.txt
env2installer/thirdparty.json
env2installer-0.12.dist-info/LICENSE.rst
env2installer-0.12.dist-info/METADATA
env2installer-0.12.dist-info/WHEEL
env2installer-0.12.dist-info/top_level.txt
env2installer-0.12.dist-info/RECORD
